notes_extractor/__init__.py
notes_extractor/__main__.py
notes_extractor/config.py
notes_extractor/constants.py
notes_extractor/exceptions.py
notes_extractor/cli/__init__.py
notes_extractor/cli/main.py
notes_extractor/core/__init__.py
notes_extractor/core/heuristics.py
notes_extractor/core/mapper.py
notes_extractor/core/normalizer.py
notes_extractor/core/parser.py
notes_extractor/core/patterns.py
notes_extractor/exporters/__init__.py
notes_extractor/exporters/base.py
notes_extractor/exporters/excel_exporter.py
notes_extractor/exporters/json_exporter.py
notes_extractor/extractors/__init__.py
notes_extractor/extractors/base.py
notes_extractor/extractors/pdfplumber_extractor.py
notes_extractor/extractors/pymupdf_extractor.py
notes_extractor/extractors/pypdf2_extractor.py
notes_extractor/models/__init__.py
notes_extractor/models/extraction_result.py
notes_extractor/models/index_page.py
notes_extractor/models/note_entry.py
notes_extractor/pipeline/__init__.py
notes_extractor/pipeline/orchestrator.py
notes_extractor/pipeline/stages.py
notes_extractor/utils/__init__.py
notes_extractor/utils/file_utils.py
notes_extractor/utils/logger.py
notes_extractor/utils/text_utils.py
notes_extractor/utils/validators.py
pdf_notes_extractor-1.0.1.dist-info/licenses/LICENSE
pdf_notes_extractor-1.0.1.dist-info/METADATA
pdf_notes_extractor-1.0.1.dist-info/WHEEL
pdf_notes_extractor-1.0.1.dist-info/entry_points.txt
pdf_notes_extractor-1.0.1.dist-info/top_level.txt
pdf_notes_extractor-1.0.1.dist-info/RECORD
